sanic_redis/__init__.py
sanic_redis/_version.py
sanic_redis/core.py
sanic_redis-0.6.0.dist-info/licenses/LICENSE
sanic_redis-0.6.0.dist-info/METADATA
sanic_redis-0.6.0.dist-info/WHEEL
sanic_redis-0.6.0.dist-info/top_level.txt
sanic_redis-0.6.0.dist-info/RECORD
