Metadata-Version: 2.4
Name: sanic-redis
Version: 0.6.0
Summary: Adds redis support to Sanic
Author-email: octal <octalgah@gmail.com>
License: MIT
Project-URL: Homepage, https://github.com/strahe/sanic-redis
Keywords: sanic,redis,hiredis
Classifier: Development Status :: 4 - Beta
Classifier: Environment :: Web Environment
Classifier: License :: OSI Approved :: MIT License
Classifier: Programming Language :: Python :: 3.9
Classifier: Programming Language :: Python :: 3.10
Classifier: Programming Language :: Python :: 3.11
Classifier: Programming Language :: Python :: 3.12
Classifier: Programming Language :: Python :: 3.13
Classifier: Programming Language :: Python :: 3 :: Only
Classifier: Topic :: Internet :: WWW/HTTP :: Session
Requires-Python: >=3.9
License-File: LICENSE
Requires-Dist: sanic>=25.0.0
Requires-Dist: redis<7.0,>=6.0.0
Requires-Dist: hiredis<4.0,>=3.0.0
Provides-Extra: test
Requires-Dist: sanic-testing>=24.6.0; extra == "test"
Requires-Dist: pytest>=7.0.0; extra == "test"
Requires-Dist: coverage; extra == "test"
Requires-Dist: pytest-asyncio; extra == "test"
Requires-Dist: ruff; extra == "test"
Dynamic: license-file
